{"document":{"xmlns":"http://www.abbyy.com/FineReader_xml/FineReader10-schema-v1.xml","languages":"","xsi:schemaLocation":"http://www.abbyy.com/FineReader_xml/FineReader10-schema-v1.xml http://www.abbyy.com/FineReader_xml/FineReader10-schema-v1.xml","producer":"ABBYY FineReader Engine 11","xmlns:xsi":"http://www.w3.org/2001/XMLSchema-instance","page":{"width":2480,"block":[{"r":2456,"b":611,"t":209,"blockName":"","blockType":"Text","text":{"par":[{"line":{"r":2143,"b":434,"t":345,"baseline":415,"l":476,"formatting":{"charParams":[{"r":534,"b":424,"t":356,"suspicious":1,"l":476,"content":"t"},{"r":534,"b":424,"t":356,"suspicious":1,"l":476,"content":"f"},{"r":585,"b":424,"t":376,"suspicious":1,"l":547,"content":"A"},{"r":639,"b":425,"t":384,"suspicious":1,"l":603,"content":"u"},{"r":752,"b":432,"t":384,"l":640},{"r":856,"b":431,"t":428,"isTab":1,"l":753,"content":"_"},{"r":888,"b":425,"t":376,"l":857,"content":4},{"r":907,"b":425,"t":376,"l":889},{"r":917,"b":422,"t":406,"suspicious":1,"l":908,"content":"<"},{"r":946,"b":424,"t":372,"suspicious":1,"l":916,"content":"g"},{"r":953,"b":393,"t":390,"suspicious":1,"l":944,"content":"'"},{"r":1176,"b":431,"t":389,"isTab":1,"l":954},{"r":1697,"b":432,"t":425,"isTab":1,"l":1177,"content":"_"},{"r":1745,"b":396,"t":348,"suspicious":1,"l":1721,"content":"G"},{"r":1767,"b":403,"t":373,"suspicious":1,"l":1745,"content":"i"},{"r":1873,"b":403,"t":362,"l":1768},{"r":1907,"b":399,"t":362,"suspicious":1,"l":1874,"content":"o"},{"r":1920,"b":401,"t":356,"l":1908},{"r":1952,"b":401,"t":356,"suspicious":1,"l":1921,"content":4},{"r":1959,"b":385,"t":372,"suspicious":1,"l":1952,"content":">"},{"r":1974,"b":406,"t":355,"l":1960},{"r":2013,"b":406,"t":355,"l":1975,"content":3},{"r":2047,"b":405,"t":352,"suspicious":1,"l":2018,"content":6},{"r":2074,"b":404,"t":375,"suspicious":1,"l":2056,"content":"i"},{"r":2114,"b":405,"t":357,"suspicious":1,"l":2073,"content":"T"},{"r":2143,"b":359,"t":356,"suspicious":1,"l":2113,"content":"~"}],"lang":"EnglishUnitedStates"}},"align":"Justified","lineSpacing":2100},{"leftIndent":9100,"line":{"r":1412,"b":603,"t":545,"baseline":595,"l":852,"formatting":{"charParams":[{"r":881,"b":589,"t":548,"l":852,"content":"F"},{"r":928,"b":591,"t":548,"suspicious":1,"l":887,"content":"O"},{"r":972,"b":591,"t":548,"l":935,"content":"R"},{"r":1023,"b":589,"t":550,"l":980,"content":"M"},{"r":1050,"b":575,"t":568,"l":1029,"content":"-"},{"r":1090,"b":590,"t":548,"l":1055,"content":"B"},{"r":1115,"b":601,"t":547,"l":1091},{"r":1133,"b":601,"t":547,"l":1116,"content":"("},{"r":1175,"b":591,"t":548,"l":1140,"content":"C"},{"r":1206,"b":590,"t":547,"l":1178,"content":"E"},{"r":1245,"b":590,"t":550,"l":1213,"content":"N"},{"r":1282,"b":590,"t":548,"l":1251,"content":"T"},{"r":1322,"b":590,"t":551,"l":1288,"content":"R"},{"r":1356,"b":590,"t":550,"l":1322,"content":"A"},{"r":1389,"b":591,"t":549,"l":1363,"content":"L"},{"r":1412,"b":601,"t":547,"l":1393,"content":")"}],"lang":"EnglishUnitedStates"}},"lineSpacing":1450}]},"l":470,"region":{"rect":[{"r":1385,"b":210,"t":209,"l":1328},{"r":1485,"b":211,"t":210,"l":1138},{"r":1591,"b":212,"t":211,"l":933},{"r":2016,"b":213,"t":212,"l":831},{"r":2455,"b":214,"t":213,"l":470},{"r":2455,"b":241,"t":214,"l":470},{"r":2456,"b":607,"t":241,"l":470},{"r":2456,"b":608,"t":607,"l":470},{"r":2456,"b":609,"t":608,"l":470},{"r":2456,"b":610,"t":609,"l":470},{"r":703,"b":611,"t":610,"l":611}]}},{"r":1606,"b":707,"t":597,"blockName":"","blockType":"Text","text":{"par":{"leftIndent":100,"line":[{"r":1534,"b":650,"t":604,"baseline":644,"l":755,"formatting":{"charParams":[{"r":767,"b":646,"t":607,"l":755,"content":"("},{"r":794,"b":641,"t":609,"l":770,"content":"S"},{"r":820,"b":641,"t":616,"l":797,"content":"e"},{"r":841,"b":640,"t":615,"l":820,"content":"e"},{"r":855,"b":640,"t":615,"l":842},{"r":875,"b":640,"t":615,"l":856,"content":"s"},{"r":897,"b":640,"t":617,"l":876,"content":"u"},{"r":922,"b":641,"t":607,"l":900,"content":"b"},{"r":939,"b":647,"t":607,"l":923},{"r":963,"b":647,"t":615,"l":940,"content":"p"},{"r":984,"b":640,"t":615,"l":963,"content":"a"},{"r":1003,"b":639,"t":616,"l":988,"content":"r"},{"r":1027,"b":640,"t":616,"l":1005,"content":"a"},{"r":1048,"b":647,"t":616,"l":1027,"content":"g"},{"r":1066,"b":639,"t":616,"l":1051,"content":"r"},{"r":1090,"b":640,"t":616,"l":1069,"content":"a"},{"r":1113,"b":647,"t":616,"l":1091,"content":"p"},{"r":1136,"b":640,"t":608,"l":1113,"content":"h"},{"r":1154,"b":648,"t":607,"l":1137},{"r":1168,"b":648,"t":607,"l":1155,"content":"("},{"r":1193,"b":639,"t":608,"l":1173,"content":3},{"r":1211,"b":647,"t":607,"l":1198,"content":")"},{"r":1226,"b":647,"t":607,"l":1212},{"r":1248,"b":640,"t":616,"l":1227,"content":"o"},{"r":1264,"b":639,"t":608,"l":1251,"content":"f"},{"r":1279,"b":647,"t":608,"l":1265},{"r":1303,"b":647,"t":617,"l":1280,"content":"p"},{"r":1324,"b":641,"t":616,"l":1303,"content":"a"},{"r":1340,"b":639,"t":617,"l":1327,"content":"r"},{"r":1365,"b":640,"t":616,"l":1344,"content":"a"},{"r":1387,"b":647,"t":617,"l":1365,"content":"g"},{"r":1406,"b":639,"t":617,"l":1392,"content":"r"},{"r":1428,"b":641,"t":617,"l":1406,"content":"a"},{"r":1453,"b":647,"t":617,"l":1430,"content":"p"},{"r":1475,"b":640,"t":607,"l":1453,"content":"h"},{"r":1493,"b":640,"t":608,"l":1476},{"r":1517,"b":639,"t":610,"l":1494,"content":4},{"r":1534,"b":646,"t":608,"suspicious":1,"l":1521,"content":")"}],"lang":"EnglishUnitedStates"}},{"r":1600,"b":693,"t":654,"baseline":691,"l":698,"formatting":{"charParams":[{"r":722,"b":686,"t":657,"l":698,"content":"P"},{"r":754,"b":686,"t":657,"l":726,"content":"U"},{"r":786,"b":686,"t":657,"l":762,"content":"B"},{"r":810,"b":686,"t":657,"l":790,"content":"L"},{"r":830,"b":686,"t":657,"l":815,"content":"I"},{"r":860,"b":687,"t":657,"l":836,"content":"C"},{"r":875,"b":687,"t":657,"l":861},{"r":900,"b":686,"t":657,"l":876,"content":"P"},{"r":930,"b":686,"t":657,"l":906,"content":"R"},{"r":966,"b":686,"t":656,"l":934,"content":"O"},{"r":994,"b":686,"t":657,"l":968,"content":"V"},{"r":1016,"b":686,"t":657,"l":1000,"content":"I"},{"r":1048,"b":686,"t":657,"l":1020,"content":"D"},{"r":1072,"b":686,"t":657,"l":1052,"content":"E"},{"r":1106,"b":686,"t":657,"l":1079,"content":"N"},{"r":1134,"b":686,"t":657,"l":1110,"content":"T"},{"r":1151,"b":686,"t":657,"l":1135},{"r":1172,"b":686,"t":656,"l":1152,"content":"F"},{"r":1202,"b":687,"t":657,"l":1176,"content":"U"},{"r":1236,"b":686,"t":657,"l":1210,"content":"N"},{"r":1270,"b":686,"t":657,"l":1242,"content":"D"},{"r":1281,"b":688,"t":657,"l":1271},{"r":1308,"b":688,"t":657,"l":1282,"content":"S"},{"r":1338,"b":688,"t":657,"l":1312,"content":"C"},{"r":1368,"b":686,"t":657,"l":1342,"content":"H"},{"r":1396,"b":686,"t":657,"l":1374,"content":"E"},{"r":1432,"b":686,"t":657,"l":1402,"content":"M"},{"r":1460,"b":687,"t":657,"l":1440,"content":"E"},{"r":1472,"b":690,"t":679,"l":1462,"content":","},{"r":1493,"b":690,"t":657,"l":1473},{"r":1513,"b":686,"t":657,"l":1494,"content":1},{"r":1544,"b":687,"t":657,"l":1520,"content":9},{"r":1572,"b":688,"t":657,"suspicious":1,"l":1548,"content":6},{"r":1600,"b":688,"t":657,"suspicious":1,"l":1576,"content":8}],"lang":"EnglishUnitedStates"}}],"align":"Center","lineSpacing":1104}},"l":692,"region":{"rect":[{"r":1476,"b":598,"t":597,"l":1149},{"r":1584,"b":599,"t":598,"l":939},{"r":1606,"b":600,"t":599,"l":829},{"r":1606,"b":601,"t":600,"l":702},{"r":1606,"b":703,"t":601,"l":692},{"r":1606,"b":704,"t":703,"l":692},{"r":1606,"b":705,"t":704,"l":692},{"r":836,"b":706,"t":705,"l":692},{"r":701,"b":707,"t":706,"l":692}]}},{"r":2156,"b":2637,"t":690,"blockName":"","blockType":"Table","row":[{"cell":[{"bottomBorder":"White","width":218,"text":{"par":{"leftIndent":1200,"line":{"r":493,"b":813,"t":712,"baseline":790,"l":355,"formatting":{"charParams":[{"r":399,"b":813,"t":716,"suspicious":1,"l":355,"content":1},{"r":493,"b":813,"t":712,"suspicious":1,"l":427,"content":1}],"lang":"EnglishUnitedStates"}},"lineSpacing":1550}},"height":97},{"colSpan":2,"width":1633,"text":{"par":{"leftIndent":16500,"line":{"r":1602,"b":763,"t":725,"baseline":764,"l":1210,"formatting":{"charParams":[{"r":1238,"b":761,"t":727,"l":1210,"content":"C"},{"r":1273,"b":760,"t":727,"l":1239,"content":"O"},{"r":1304,"b":760,"t":727,"l":1275,"content":"U"},{"r":1343,"b":761,"t":727,"l":1311,"content":"N"},{"r":1374,"b":761,"t":727,"l":1343,"content":"T"},{"r":1403,"b":761,"t":726,"l":1377,"content":"E"},{"r":1436,"b":761,"t":726,"l":1406,"content":"R"},{"r":1463,"b":761,"t":726,"l":1439,"content":"F"},{"r":1500,"b":761,"t":727,"l":1466,"content":"O"},{"r":1522,"b":760,"t":727,"l":1502,"content":"I"},{"r":1551,"b":760,"t":727,"l":1527,"content":"L"},{"r":1572,"b":750,"t":742,"l":1554,"content":"-"},{"r":1602,"b":761,"t":727,"l":1576,"content":2}],"lang":"EnglishUnitedStates"}},"lineSpacing":1160}},"height":97}]},{"cell":[{"topBorder":"White","width":218,"text":{"par":{"leftIndent":1200,"line":{"r":495,"b":853,"t":764,"baseline":848,"l":349,"formatting":{"charParams":[{"r":421,"b":853,"t":764,"suspicious":1,"l":349,"content":"%"},{"r":495,"b":853,"t":772,"suspicious":1,"l":425,"content":"w"}],"lang":"EnglishUnitedStates"}},"lineSpacing":1440}},"height":90},{"colSpan":2,"width":1633,"text":{"par":{"leftIndent":100,"line":{"r":1542,"b":858,"t":814,"baseline":860,"l":1128,"formatting":{"charParams":[{"r":1166,"b":856,"t":815,"l":1128,"content":"B"},{"r":1210,"b":856,"t":815,"l":1168,"content":"A"},{"r":1250,"b":856,"t":814,"l":1212,"content":"N"},{"r":1298,"b":855,"t":815,"l":1256,"content":"K"},{"r":1316,"b":836,"t":814,"l":1300,"content":"\u2019"},{"r":1354,"b":855,"t":815,"l":1318,"content":"S"},{"r":1375,"b":855,"t":815,"l":1355},{"r":1414,"b":855,"t":815,"l":1376,"content":"C"},{"r":1458,"b":857,"t":814,"l":1417,"content":"O"},{"r":1500,"b":856,"t":815,"l":1464,"content":"P"},{"r":1542,"b":856,"t":815,"l":1502,"content":"Y"}],"lang":"EnglishUnitedStates"}},"align":"Center","lineSpacing":1550}},"height":90}]},{"cell":[{"colSpan":2,"rightBorder":"White","width":1108,"text":{"par":{"leftIndent":700,"line":{"r":817,"b":947,"t":908,"baseline":947,"l":332,"formatting":{"charParams":[{"r":361,"b":946,"t":909,"l":332,"content":"S"},{"r":393,"b":945,"t":909,"l":364,"content":"B"},{"r":412,"b":945,"t":909,"suspicious":1,"l":396,"content":"I"},{"r":432,"b":945,"t":909,"l":413},{"r":461,"b":945,"t":909,"l":433,"content":"B"},{"r":493,"b":945,"t":909,"l":465,"content":"R"},{"r":526,"b":945,"t":909,"l":493,"content":"A"},{"r":560,"b":944,"t":909,"l":530,"content":"N"},{"r":594,"b":945,"t":909,"l":563,"content":"C"},{"r":627,"b":946,"t":908,"l":597,"content":"H"},{"r":646,"b":946,"t":909,"l":628},{"r":678,"b":946,"t":909,"l":647,"content":"N"},{"r":711,"b":946,"t":908,"l":681,"content":"A"},{"r":750,"b":945,"t":908,"l":716,"content":"M"},{"r":781,"b":945,"t":908,"l":756,"content":"E"},{"r":805,"b":946,"t":908,"l":782},{"r":817,"b":946,"t":919,"l":806,"content":":"}],"lang":"EnglishUnitedStates"}},"lineSpacing":1550}},"height":93},{"leftBorder":"White","width":743,"text":{"par":{"rightIndent":2200,"line":{"r":2064,"b":946,"t":896,"baseline":944,"l":1572,"formatting":{"charParams":[{"r":1603,"b":945,"t":908,"l":1572,"content":"D"},{"r":1630,"b":945,"t":917,"l":1606,"content":"a"},{"r":1650,"b":946,"t":910,"l":1630,"content":"t"},{"r":1676,"b":946,"t":918,"l":1650,"content":"e"},{"r":1694,"b":946,"t":919,"l":1684,"content":":"},{"r":1736,"b":946,"t":900,"l":1695},{"r":1763,"b":937,"t":900,"l":1737,"content":2},{"r":1794,"b":937,"t":897,"l":1765,"content":5},{"r":1806,"b":944,"t":897,"l":1795},{"r":1822,"b":944,"t":907,"l":1807,"content":"/"},{"r":1849,"b":944,"t":900,"l":1823},{"r":1875,"b":937,"t":900,"l":1850,"content":0},{"r":1901,"b":937,"t":900,"l":1874,"content":2},{"r":1917,"b":944,"t":900,"l":1902},{"r":1934,"b":944,"t":910,"l":1918,"content":"/"},{"r":1966,"b":946,"t":910,"l":1940,"content":2},{"r":1995,"b":946,"t":910,"l":1967,"content":0},{"r":2010,"b":946,"t":899,"l":1996},{"r":2035,"b":937,"t":899,"suspicious":1,"l":2011,"content":"I"},{"r":2064,"b":938,"t":899,"suspicious":1,"l":2038,"content":"S"}],"lang":"EnglishUnitedStates"}},"align":"Right","lineSpacing":1550}},"height":93}]},{"cell":{"colSpan":3,"width":1851,"text":{"par":{"leftIndent":700,"line":{"r":1361,"b":1044,"t":983,"baseline":1032,"l":332,"formatting":{"charParams":[{"r":362,"b":1022,"t":988,"l":332,"content":"N"},{"r":396,"b":1023,"t":988,"l":364,"content":"A"},{"r":434,"b":1023,"t":988,"l":400,"content":"M"},{"r":465,"b":1023,"t":988,"l":439,"content":"E"},{"r":483,"b":1024,"t":987,"l":466},{"r":518,"b":1024,"t":987,"l":484,"content":"O"},{"r":546,"b":1023,"t":988,"l":523,"content":"F"},{"r":564,"b":1023,"t":986,"l":547},{"r":594,"b":1023,"t":986,"l":565,"content":"S"},{"r":626,"b":1025,"t":987,"l":597,"content":"U"},{"r":659,"b":1023,"t":988,"l":631,"content":"B"},{"r":692,"b":1024,"t":987,"l":662,"content":"S"},{"r":724,"b":1024,"t":987,"l":694,"content":"C"},{"r":758,"b":1022,"t":987,"l":728,"content":"R"},{"r":777,"b":1022,"t":988,"l":760,"content":"I"},{"r":809,"b":1023,"t":988,"l":782,"content":"B"},{"r":839,"b":1023,"t":988,"l":814,"content":"E"},{"r":872,"b":1023,"t":987,"l":842,"content":"R"},{"r":889,"b":1023,"t":996,"l":877,"content":":"},{"r":996,"b":1041,"t":996,"isTab":1,"l":890},{"r":1022,"b":1041,"t":1001,"l":997,"content":"S"},{"r":1066,"b":1041,"t":1001,"l":1028,"content":"R"},{"r":1085,"b":1041,"t":1001,"l":1068,"content":"I"},{"r":1129,"b":1041,"t":1000,"suspicious":1,"l":1090,"content":"K"},{"r":1169,"b":1041,"t":1001,"l":1131,"content":"R"},{"r":1188,"b":1040,"t":1001,"l":1172,"content":"I"},{"r":1219,"b":1040,"t":1001,"l":1194,"content":"S"},{"r":1266,"b":1041,"t":1001,"l":1225,"content":"H"},{"r":1316,"b":1041,"t":1001,"l":1271,"content":"N"},{"r":1361,"b":1041,"t":1001,"l":1319,"content":"A"}],"lang":"EnglishUnitedStates"}},"align":"Justified","lineSpacing":1550}},"height":91}},{"cell":{"colSpan":3,"width":1851,"text":{"par":{"leftIndent":700,"line":{"r":1319,"b":1136,"t":1084,"baseline":1130,"l":333,"formatting":{"charParams":[{"r":364,"b":1129,"t":1092,"l":333,"content":"P"},{"r":397,"b":1129,"t":1092,"l":367,"content":"P"},{"r":427,"b":1129,"t":1092,"l":400,"content":"F"},{"r":444,"b":1129,"t":1092,"l":428},{"r":480,"b":1129,"t":1092,"l":445,"content":"A"},{"r":508,"b":1135,"t":1090,"l":483,"content":"/"},{"r":544,"b":1129,"t":1091,"l":512,"content":"C"},{"r":564,"b":1129,"t":1091,"l":545},{"r":598,"b":1129,"t":1092,"l":565,"content":"N"},{"r":640,"b":1129,"t":1091,"l":603,"content":"O"},{"r":754,"b":1130,"t":1091,"isTab":1,"l":641},{"r":766,"b":1129,"t":1100,"l":755,"content":":"},{"r":1011,"b":1129,"t":1085,"isTab":1,"l":767},{"r":1038,"b":1125,"t":1085,"l":1012,"content":2},{"r":1066,"b":1125,"t":1086,"l":1043,"content":8},{"r":1094,"b":1126,"t":1086,"l":1071,"content":3},{"r":1125,"b":1126,"t":1086,"l":1100,"content":2},{"r":1142,"b":1126,"t":1086,"l":1126},{"r":1169,"b":1126,"t":1085,"l":1143,"content":6},{"r":1198,"b":1125,"t":1085,"l":1175,"content":9},{"r":1225,"b":1125,"t":1085,"l":1203,"content":3},{"r":1242,"b":1126,"t":1085,"l":1226},{"r":1268,"b":1126,"t":1086,"l":1243,"content":2},{"r":1290,"b":1126,"t":1086,"l":1274,"content":1},{"r":1319,"b":1130,"t":1086,"suspicious":1,"l":1293,"content":7}],"lang":"EnglishUnitedStates"}},"align":"Justified","lineSpacing":1550}},"height":90}},{"cell":{"colSpan":3,"width":1851,"text":{"par":{"line":{"r":1605,"b":1200,"t":1164,"baseline":1197,"l":853,"formatting":{"charParams":[{"r":880,"b":1194,"t":1167,"l":853,"content":"A"},{"r":911,"b":1195,"t":1166,"l":882,"content":"M"},{"r":943,"b":1194,"t":1165,"l":914,"content":"O"},{"r":971,"b":1194,"t":1167,"l":945,"content":"U"},{"r":1003,"b":1195,"t":1166,"l":976,"content":"N"},{"r":1028,"b":1194,"t":1166,"l":1002,"content":"T"},{"r":1038,"b":1194,"t":1165,"l":1028},{"r":1066,"b":1194,"t":1165,"l":1038,"content":"O"},{"r":1091,"b":1193,"t":1167,"l":1070,"content":"F"},{"r":1102,"b":1194,"t":1167,"l":1091},{"r":1129,"b":1194,"t":1167,"l":1102,"content":"D"},{"r":1153,"b":1194,"t":1167,"l":1131,"content":"E"},{"r":1180,"b":1195,"t":1166,"l":1156,"content":"P"},{"r":1208,"b":1195,"t":1165,"l":1179,"content":"O"},{"r":1235,"b":1194,"t":1165,"l":1207,"content":"S"},{"r":1255,"b":1194,"t":1167,"l":1236,"content":"I"},{"r":1279,"b":1193,"t":1167,"l":1254,"content":"T"},{"r":1290,"b":1194,"t":1167,"l":1279},{"r":1316,"b":1194,"t":1167,"l":1290,"content":"C"},{"r":1342,"b":1194,"t":1168,"l":1315,"content":"A"},{"r":1367,"b":1195,"t":1166,"l":1342,"content":"S"},{"r":1395,"b":1194,"t":1168,"l":1369,"content":"H"},{"r":1412,"b":1198,"t":1165,"l":1396},{"r":1430,"b":1198,"t":1165,"l":1413,"content":"/"},{"r":1443,"b":1198,"t":1165,"l":1431},{"r":1469,"b":1195,"t":1165,"l":1444,"content":"C"},{"r":1499,"b":1195,"t":1167,"l":1473,"content":"H"},{"r":1524,"b":1195,"t":1167,"l":1502,"content":"E"},{"r":1553,"b":1199,"t":1166,"l":1525,"content":"Q"},{"r":1581,"b":1195,"t":1166,"l":1555,"content":"U"},{"r":1605,"b":1195,"t":1166,"l":1584,"content":"E"}],"lang":"EnglishUnitedStates"}},"align":"Center","lineSpacing":1550}},"height":52}},{"cell":[{"colSpan":2,"width":1108,"text":{"par":{"line":{"r":727,"b":1270,"t":1234,"baseline":1269,"l":332,"formatting":{"charParams":[{"r":360,"b":1269,"t":1234,"l":332,"content":"S"},{"r":393,"b":1268,"t":1236,"l":363,"content":"U"},{"r":427,"b":1268,"t":1236,"l":398,"content":"B"},{"r":457,"b":1269,"t":1235,"l":431,"content":"S"},{"r":488,"b":1268,"t":1234,"l":461,"content":"C"},{"r":522,"b":1268,"t":1235,"l":493,"content":"R"},{"r":543,"b":1268,"t":1236,"l":522,"content":"I"},{"r":577,"b":1267,"t":1234,"l":549,"content":"P"},{"r":603,"b":1267,"t":1236,"l":577,"content":"T"},{"r":627,"b":1268,"t":1235,"l":603,"content":"I"},{"r":662,"b":1268,"t":1235,"l":631,"content":"O"},{"r":698,"b":1268,"t":1235,"l":669,"content":"N"},{"r":727,"b":1256,"t":1234,"l":707,"content":"*"}],"lang":"EnglishUnitedStates"}},"lineSpacing":1160}},"height":91},{"width":743,"text":{"par":{"line":{"r":1822,"b":1281,"t":1226,"baseline":1276,"l":1426,"formatting":{"charParams":[{"r":1467,"b":1280,"t":1226,"suspicious":1,"l":1426,"content":"^"},{"r":1601,"b":1281,"t":1227,"isTab":1,"l":1468},{"r":1624,"b":1274,"t":1234,"l":1602,"content":3},{"r":1658,"b":1274,"t":1234,"l":1631,"content":4},{"r":1690,"b":1273,"t":1234,"l":1664,"content":0},{"r":1718,"b":1273,"t":1233,"l":1696,"content":9},{"r":1751,"b":1274,"t":1233,"l":1725,"content":2},{"r":1759,"b":1273,"t":1269,"l":1755,"content":","},{"r":1790,"b":1273,"t":1234,"l":1765,"content":0},{"r":1822,"b":1274,"t":1233,"l":1795,"content":0}],"lang":"EnglishUnitedStates"}},"align":"Justified","lineSpacing":1550}},"height":91}]},{"cell":[{"colSpan":2,"width":1108,"text":{"par":{"line":{"r":747,"b":1360,"t":1324,"baseline":1359,"l":333,"formatting":{"charParams":[{"r":354,"b":1358,"t":1325,"l":333,"content":"L"},{"r":386,"b":1359,"t":1325,"l":355,"content":"O"},{"r":417,"b":1358,"t":1325,"l":389,"content":"A"},{"r":446,"b":1358,"t":1325,"l":421,"content":"N"},{"r":464,"b":1358,"t":1325,"l":447},{"r":492,"b":1358,"t":1325,"l":465,"content":"R"},{"r":518,"b":1358,"t":1325,"l":496,"content":"E"},{"r":546,"b":1357,"t":1325,"l":521,"content":"P"},{"r":576,"b":1357,"t":1324,"l":548,"content":"A"},{"r":604,"b":1360,"t":1324,"l":578,"content":"Y"},{"r":634,"b":1358,"t":1325,"l":604,"content":"M"},{"r":661,"b":1359,"t":1325,"l":640,"content":"E"},{"r":693,"b":1358,"t":1324,"l":665,"content":"N"},{"r":722,"b":1357,"t":1325,"l":696,"content":"T"},{"r":747,"b":1345,"t":1325,"l":726,"content":"*"}],"lang":"EnglishUnitedStates"}},"lineSpacing":1160}},"height":90},{"width":743,"text":{"par":{"line":{"r":1812,"b":1367,"t":1313,"baseline":1360,"l":1426,"formatting":{"charParams":[{"r":1467,"b":1366,"t":1315,"suspicious":1,"l":1426,"content":"^"},{"r":1605,"b":1367,"t":1314,"isTab":1,"l":1468},{"r":1630,"b":1356,"t":1315,"l":1606,"content":2},{"r":1659,"b":1355,"t":1315,"l":1637,"content":3},{"r":1688,"b":1355,"t":1315,"l":1665,"content":9},{"r":1715,"b":1359,"t":1314,"l":1690,"content":7},{"r":1746,"b":1355,"t":1315,"l":1718,"content":4},{"r":1755,"b":1355,"t":1349,"l":1753,"content":","},{"r":1783,"b":1356,"t":1315,"l":1761,"content":8},{"r":1812,"b":1358,"t":1315,"l":1787,"content":7}],"lang":"EnglishUnitedStates"}},"align":"Justified","lineSpacing":1550}},"height":90}]},{"cell":[{"colSpan":2,"width":1108,"text":{"par":{"line":{"r":787,"b":1451,"t":1416,"baseline":1451,"l":331,"formatting":{"charParams":[{"r":346,"b":1450,"t":1418,"l":331,"content":"I"},{"r":378,"b":1450,"t":1418,"l":350,"content":"N"},{"r":406,"b":1450,"t":1418,"l":378,"content":"T"},{"r":432,"b":1450,"t":1418,"l":408,"content":"E"},{"r":461,"b":1449,"t":1418,"l":436,"content":"R"},{"r":487,"b":1450,"t":1417,"l":464,"content":"E"},{"r":519,"b":1449,"t":1417,"l":492,"content":"S"},{"r":546,"b":1449,"t":1418,"l":519,"content":"T"},{"r":562,"b":1450,"t":1417,"l":547},{"r":594,"b":1451,"t":1417,"l":563,"content":"O"},{"r":625,"b":1450,"t":1418,"l":598,"content":"N"},{"r":643,"b":1450,"t":1418,"l":626},{"r":665,"b":1450,"t":1418,"l":644,"content":"L"},{"r":699,"b":1450,"t":1416,"l":667,"content":"O"},{"r":727,"b":1448,"t":1418,"l":700,"content":"A"},{"r":759,"b":1449,"t":1417,"l":732,"content":"N"},{"r":787,"b":1439,"t":1416,"l":766,"content":"*"}],"lang":"EnglishUnitedStates"}},"lineSpacing":1160}},"height":92},{"width":743,"text":{"par":{"line":{"r":1821,"b":1460,"t":1407,"baseline":1461,"l":1424,"formatting":{"charParams":[{"r":1465,"b":1457,"t":1407,"suspicious":1,"l":1424,"content":"^"},{"r":1608,"b":1458,"t":1407,"isTab":1,"l":1466},{"r":1633,"b":1458,"t":1419,"l":1609,"content":0},{"r":1656,"b":1459,"t":1418,"l":1639,"content":1},{"r":1688,"b":1459,"t":1419,"l":1661,"content":2},{"r":1716,"b":1458,"t":1419,"l":1693,"content":3},{"r":1749,"b":1459,"t":1419,"l":1722,"content":4},{"r":1759,"b":1458,"t":1454,"l":1755,"content":","},{"r":1790,"b":1458,"t":1419,"l":1765,"content":5},{"r":1821,"b":1460,"t":1419,"l":1795,"content":6}],"lang":"EnglishUnitedStates"}},"align":"Justified","lineSpacing":1550}},"height":92}]},{"cell":[{"colSpan":2,"width":1108,"text":{"par":{"line":{"r":701,"b":1548,"t":1508,"baseline":1543,"l":332,"formatting":{"charParams":[{"r":354,"b":1542,"t":1509,"l":332,"content":"P"},{"r":381,"b":1542,"t":1509,"l":358,"content":"E"},{"r":411,"b":1542,"t":1509,"l":385,"content":"N"},{"r":444,"b":1541,"t":1509,"l":414,"content":"A"},{"r":469,"b":1542,"t":1508,"l":445,"content":"L"},{"r":494,"b":1540,"t":1508,"l":468,"content":"T"},{"r":520,"b":1541,"t":1509,"l":494,"content":"Y"},{"r":536,"b":1547,"t":1508,"l":521},{"r":553,"b":1547,"t":1508,"l":537,"content":"/"},{"r":573,"b":1548,"t":1508,"l":554},{"r":593,"b":1542,"t":1509,"l":574,"content":"F"},{"r":621,"b":1542,"t":1509,"l":599,"content":"E"},{"r":646,"b":1541,"t":1509,"l":624,"content":"E"},{"r":677,"b":1543,"t":1509,"l":649,"content":"S"},{"r":701,"b":1530,"t":1509,"l":681,"content":"*"}],"lang":"EnglishUnitedStates"}},"lineSpacing":1550}},"height":91},{"width":743,"text":{"par":{"line":{"r":1808,"b":1547,"t":1494,"baseline":1545,"l":1423,"formatting":{"charParams":[{"r":1463,"b":1544,"t":1494,"suspicious":1,"l":1423,"content":"^"},{"r":1607,"b":1545,"t":1494,"isTab":1,"l":1464},{"r":1633,"b":1543,"t":1503,"l":1608,"content":6},{"r":1661,"b":1546,"t":1503,"l":1636,"content":7},{"r":1687,"b":1544,"t":1503,"l":1664,"content":8},{"r":1716,"b":1544,"t":1503,"l":1692,"content":9},{"r":1746,"b":1544,"t":1503,"l":1720,"content":0},{"r":1755,"b":1544,"t":1538,"suspicious":1,"l":1752,"content":","},{"r":1777,"b":1544,"t":1504,"l":1761,"content":1},{"r":1808,"b":1544,"t":1504,"l":1783,"content":2}],"lang":"EnglishUnitedStates"}},"align":"Justified","lineSpacing":1550}},"height":91}]},{"cell":[{"colSpan":2,"width":1108,"text":{"par":{"line":{"r":708,"b":1634,"t":1599,"baseline":1635,"l":330,"formatting":{"charParams":[{"r":358,"b":1633,"t":1600,"l":330,"content":"T"},{"r":394,"b":1633,"t":1600,"l":360,"content":"O"},{"r":423,"b":1633,"t":1600,"l":396,"content":"T"},{"r":456,"b":1632,"t":1600,"l":425,"content":"A"},{"r":484,"b":1632,"t":1600,"l":460,"content":"L"},{"r":498,"b":1632,"t":1600,"l":485},{"r":530,"b":1632,"t":1600,"l":499,"content":"A"},{"r":568,"b":1633,"t":1599,"l":532,"content":"M"},{"r":606,"b":1633,"t":1600,"l":574,"content":"O"},{"r":640,"b":1633,"t":1600,"l":612,"content":"U"},{"r":678,"b":1633,"t":1600,"l":647,"content":"N"},{"r":708,"b":1633,"t":1599,"l":678,"content":"T"}],"lang":"EnglishUnitedStates"}},"lineSpacing":1160}},"height":91},{"width":743,"text":{"par":{"line":{"r":1808,"b":1638,"t":1584,"baseline":1635,"l":1427,"formatting":{"charParams":[{"r":1469,"b":1636,"t":1584,"suspicious":1,"l":1427,"content":"^"},{"r":1607,"b":1637,"t":1584,"isTab":1,"l":1470},{"r":1629,"b":1631,"t":1590,"l":1608,"content":3},{"r":1664,"b":1631,"t":1591,"l":1635,"content":4},{"r":1696,"b":1631,"t":1590,"l":1669,"content":2},{"r":1717,"b":1631,"t":1591,"l":1702,"content":1},{"r":1746,"b":1631,"t":1591,"l":1724,"content":3},{"r":1756,"b":1631,"t":1625,"suspicious":1,"l":1752,"content":","},{"r":1783,"b":1634,"t":1591,"l":1758,"content":7},{"r":1808,"b":1634,"t":1591,"l":1783,"content":7}],"lang":"EnglishUnitedStates"}},"align":"Justified","lineSpacing":1550}},"height":91}]},{"cell":{"colSpan":3,"bottomBorder":"White","width":1851,"text":{"par":{"line":{"r":2113,"b":1728,"t":1676,"baseline":1720,"l":329,"formatting":{"charParams":[{"r":359,"b":1727,"t":1696,"l":329,"content":"A"},{"r":398,"b":1727,"t":1704,"l":360,"content":"m"},{"r":426,"b":1727,"t":1703,"l":401,"content":"o"},{"r":452,"b":1727,"t":1705,"l":430,"content":"u"},{"r":481,"b":1727,"t":1704,"l":458,"content":"n"},{"r":496,"b":1727,"t":1698,"l":481,"content":"t"},{"r":512,"b":1727,"t":1696,"l":497},{"r":529,"b":1728,"t":1696,"l":513,"content":"I"},{"r":555,"b":1728,"t":1704,"l":533,"content":"n"},{"r":572,"b":1728,"t":1697,"l":556},{"r":613,"b":1728,"t":1697,"l":573,"content":"W"},{"r":640,"b":1728,"t":1703,"l":618,"content":"o"},{"r":658,"b":1728,"t":1705,"l":643,"content":"r"},{"r":684,"b":1728,"t":1696,"l":660,"content":"d"},{"r":709,"b":1727,"t":1703,"l":688,"content":"s"},{"r":725,"b":1727,"t":1696,"l":710},{"r":738,"b":1727,"t":1696,"suspicious":1,"l":726,"content":"l"},{"r":746,"b":1727,"t":1696,"l":739},{"r":771,"b":1727,"t":1697,"l":747,"content":"R"},{"r":797,"b":1727,"t":1706,"suspicious":1,"l":776,"content":"u"},{"r":827,"b":1727,"t":1705,"suspicious":1,"l":805,"content":"D"},{"r":850,"b":1727,"t":1705,"suspicious":1,"l":827,"content":"e"},{"r":875,"b":1727,"t":1705,"l":854,"content":"e"},{"r":899,"b":1727,"t":1705,"l":880,"content":"s"},{"r":1147,"b":1727,"t":1684,"isTab":1,"l":900},{"r":1170,"b":1709,"t":1684,"suspicious":1,"l":1148,"content":"*"},{"r":1194,"b":1709,"t":1689,"suspicious":1,"l":1169,"content":"*"},{"r":1212,"b":1709,"t":1689,"suspicious":1,"l":1195,"content":"*"},{"r":1233,"b":1709,"t":1677,"suspicious":1,"l":1213,"content":"*"},{"r":1262,"b":1709,"t":1689,"suspicious":1,"l":1232,"content":"*"},{"r":1440,"b":1710,"t":1678,"isTab":1,"l":1263},{"r":1452,"b":1709,"t":1678,"l":1441,"content":"f"},{"r":1468,"b":1709,"t":1690,"l":1452,"content":"o"},{"r":1491,"b":1709,"t":1690,"l":1472,"content":"u"},{"r":1511,"b":1709,"t":1690,"l":1494,"content":"r"},{"r":1519,"b":1709,"t":1678,"l":1512},{"r":1539,"b":1709,"t":1678,"l":1520,"content":"h"},{"r":1561,"b":1709,"t":1690,"l":1541,"content":"u"},{"r":1582,"b":1709,"t":1689,"l":1565,"content":"n"},{"r":1604,"b":1709,"t":1677,"l":1586,"content":"d"},{"r":1624,"b":1709,"t":1689,"l":1607,"content":"r"},{"r":1639,"b":1710,"t":1689,"l":1624,"content":"e"},{"r":1661,"b":1709,"t":1678,"l":1642,"content":"d"},{"r":1672,"b":1709,"t":1678,"l":1662},{"r":1689,"b":1709,"t":1690,"l":1673,"content":"a"},{"r":1712,"b":1709,"t":1690,"l":1692,"content":"n"},{"r":1733,"b":1709,"t":1678,"l":1714,"content":"d"},{"r":1744,"b":1709,"t":1678,"l":1734},{"r":1758,"b":1709,"t":1678,"l":1745,"content":"f"},{"r":1767,"b":1709,"t":1682,"l":1758,"content":"i"},{"r":1784,"b":1709,"t":1678,"l":1770,"content":"f"},{"r":1798,"b":1709,"t":1685,"l":1784,"content":"t"},{"r":1818,"b":1721,"t":1690,"l":1798,"content":"y"},{"r":1825,"b":1721,"t":1690,"l":1819},{"r":1842,"b":1709,"t":1690,"l":1826,"content":"o"},{"r":1863,"b":1709,"t":1690,"l":1845,"content":"n"},{"r":1876,"b":1709,"t":1678,"l":1866,"content":"l"},{"r":1898,"b":1720,"t":1690,"l":1879,"content":"y"},{"r":2099,"b":1727,"t":1690,"isTab":1,"l":1899},{"r":2113,"b":1727,"t":1696,"suspicious":1,"l":2100,"content":"^"}],"lang":"EnglishUnitedStates"}},"align":"Justified","lineSpacing":1550}},"height":73}},{"cell":[{"topBorder":"White","rightBorder":"White","width":218,"text":{"par":{"lineSpacing":-1}},"height":32},{"leftBorder":"White","rightBorder":"White","width":890,"text":{"par":{"lineSpacing":-1}},"height":32},{"leftBorder":"White","width":743,"text":{"par":{"lineSpacing":-1}},"height":32}]},{"cell":[{"colSpan":2,"width":1108,"text":{"par":{"leftIndent":6200,"line":{"r":1160,"b":1831,"t":1795,"baseline":1830,"l":560,"formatting":{"charParams":[{"r":589,"b":1829,"t":1797,"l":560,"content":"D"},{"r":615,"b":1829,"t":1796,"l":593,"content":"E"},{"r":643,"b":1829,"t":1796,"l":617,"content":"T"},{"r":673,"b":1829,"t":1797,"l":645,"content":"A"},{"r":690,"b":1829,"t":1797,"l":673,"content":"I"},{"r":715,"b":1828,"t":1797,"l":694,"content":"L"},{"r":744,"b":1830,"t":1797,"l":715,"content":"S"},{"r":759,"b":1831,"t":1797,"l":745},{"r":792,"b":1831,"t":1797,"l":760,"content":"O"},{"r":817,"b":1829,"t":1797,"l":797,"content":"F"},{"r":834,"b":1830,"t":1796,"l":818},{"r":863,"b":1830,"t":1796,"l":835,"content":"C"},{"r":894,"b":1829,"t":1797,"l":863,"content":"A"},{"r":921,"b":1831,"t":1796,"l":894,"content":"S"},{"r":952,"b":1829,"t":1797,"l":924,"content":"H"},{"r":970,"b":1829,"t":1797,"l":953},{"r":999,"b":1829,"t":1797,"l":971,"content":"D"},{"r":1025,"b":1829,"t":1797,"l":1003,"content":"E"},{"r":1052,"b":1830,"t":1797,"l":1029,"content":"P"},{"r":1087,"b":1831,"t":1796,"l":1055,"content":"O"},{"r":1115,"b":1830,"t":1796,"l":1088,"content":"S"},{"r":1134,"b":1829,"t":1797,"l":1117,"content":"I"},{"r":1160,"b":1829,"t":1797,"l":1134,"content":"T"}],"lang":"EnglishUnitedStates"}},"align":"Justified","lineSpacing":1160}},"height":92},{"width":743,"text":{"par":{"leftIndent":200,"line":{"r":1872,"b":1831,"t":1796,"baseline":1829,"l":1687,"formatting":{"charParams":[{"r":1714,"b":1828,"t":1797,"l":1687,"content":"A"},{"r":1749,"b":1828,"t":1797,"l":1717,"content":"M"},{"r":1782,"b":1831,"t":1797,"l":1753,"content":"O"},{"r":1811,"b":1831,"t":1797,"l":1786,"content":"U"},{"r":1843,"b":1829,"t":1798,"l":1817,"content":"N"},{"r":1872,"b":1829,"t":1797,"l":1846,"content":"T"}],"lang":"EnglishUnitedStates"}},"align":"Center","lineSpacing":1160}},"height":92}]},{"cell":[{"colSpan":2,"width":1108,"text":{"par":{"leftIndent":4100,"line":{"r":779,"b":1903,"t":1868,"baseline":1903,"l":473,"formatting":{"charParams":[{"r":493,"b":1902,"t":1870,"l":473,"content":1},{"r":521,"b":1903,"t":1868,"l":497,"content":0},{"r":549,"b":1902,"t":1869,"l":523,"content":0},{"r":576,"b":1902,"t":1868,"l":551,"content":0},{"r":750,"b":1902,"t":1868,"isTab":1,"l":577},{"r":779,"b":1902,"t":1869,"l":751,"content":"X"}],"lang":"EnglishUnitedStates"}},"align":"Justified","lineSpacing":1160}},"height":52},{"width":743,"text":{"par":{"leftIndent":1700,"line":{"r":1848,"b":1904,"t":1866,"baseline":1903,"l":1663,"formatting":{"charParams":[{"r":1682,"b":1903,"t":1866,"l":1663,"content":3},{"r":1714,"b":1903,"t":1868,"l":1688,"content":4},{"r":1742,"b":1903,"t":1866,"l":1720,"content":2},{"r":1764,"b":1903,"t":1867,"l":1748,"content":1},{"r":1786,"b":1903,"t":1868,"l":1766,"content":3},{"r":1795,"b":1903,"t":1898,"suspicious":1,"l":1791,"content":"."},{"r":1821,"b":1903,"t":1867,"suspicious":1,"l":1798,"content":7},{"r":1848,"b":1903,"t":1867,"suspicious":1,"l":1821,"content":7}],"lang":"EnglishUnitedStates"}},"align":"Center","lineSpacing":1550}},"height":52}]},{"cell":[{"colSpan":2,"width":1108,"text":{"par":{"leftIndent":4800,"line":{"r":778,"b":1956,"t":1923,"baseline":1957,"l":501,"formatting":{"charParams":[{"r":523,"b":1956,"t":1924,"l":501,"content":5},{"r":551,"b":1956,"t":1924,"l":529,"content":0},{"r":577,"b":1956,"t":1923,"l":553,"content":0},{"r":751,"b":1956,"t":1923,"isTab":1,"l":578},{"r":778,"b":1956,"t":1925,"l":752,"content":"X"}],"lang":"EnglishUnitedStates"}},"align":"Justified","lineSpacing":1060}},"height":54},{"width":743,"text":{"par":{"leftIndent":6000,"line":{"r":1832,"b":1959,"t":1922,"baseline":1959,"l":1660,"formatting":{"charParams":[{"r":1679,"b":1958,"t":1923,"l":1660,"content":3},{"r":1707,"b":1957,"t":1922,"l":1685,"content":4},{"r":1736,"b":1957,"t":1923,"l":1713,"content":2},{"r":1752,"b":1957,"t":1923,"l":1741,"content":1},{"r":1776,"b":1957,"t":1923,"l":1757,"content":3},{"r":1786,"b":1957,"t":1951,"suspicious":1,"l":1782,"content":"."},{"r":1810,"b":1959,"t":1923,"l":1788,"content":7},{"r":1832,"b":1959,"t":1923,"l":1810,"content":7}],"lang":"EnglishUnitedStates"}},"lineSpacing":1550}},"height":54}]},{"cell":[{"colSpan":2,"width":1108,"text":{"par":{"leftIndent":4800,"line":{"r":778,"b":2010,"t":1976,"baseline":2010,"l":503,"formatting":{"charParams":[{"r":523,"b":2008,"t":1976,"l":503,"content":1},{"r":553,"b":2009,"t":1977,"l":529,"content":0},{"r":577,"b":2009,"t":1977,"l":553,"content":0},{"r":751,"b":2010,"t":1977,"isTab":1,"l":578},{"r":778,"b":2010,"t":1977,"l":752,"content":"X"}],"lang":"EnglishUnitedStates"}},"align":"Justified","lineSpacing":1060}},"height":54},{"width":743,"text":{"par":{"leftIndent":6000,"line":{"r":1820,"b":2007,"t":1975,"baseline":2006,"l":1666,"formatting":{"charParams":[{"r":1682,"b":2003,"t":1976,"l":1666,"content":3},{"r":1707,"b":2003,"t":1976,"l":1688,"content":4},{"r":1733,"b":2003,"t":1976,"l":1713,"content":2},{"r":1748,"b":2003,"t":1976,"l":1738,"content":1},{"r":1770,"b":2003,"t":1976,"l":1754,"content":3},{"r":1779,"b":2003,"t":1998,"suspicious":1,"l":1775,"content":"."},{"r":1800,"b":2007,"t":1975,"l":1781,"content":7},{"r":1820,"b":2006,"t":1976,"l":1800,"content":7}],"lang":"EnglishUnitedStates"}},"lineSpacing":1110}},"height":54}]},{"cell":[{"colSpan":2,"width":1108,"text":{"par":{"leftIndent":5500,"line":{"r":779,"b":2063,"t":2029,"baseline":2063,"l":530,"formatting":{"charParams":[{"r":554,"b":2062,"t":2029,"l":530,"content":5},{"r":581,"b":2062,"t":2029,"l":557,"content":0},{"r":749,"b":2063,"t":2029,"isTab":1,"l":582},{"r":779,"b":2063,"t":2029,"l":750,"content":"X"}],"lang":"EnglishUnitedStates"}},"align":"Justified","lineSpacing":1160}},"height":54},{"width":743,"text":{"par":{"lineSpacing":-1}},"height":54}]},{"cell":[{"colSpan":2,"width":1108,"text":{"par":{"leftIndent":5500,"line":{"r":778,"b":2123,"t":2087,"baseline":2124,"l":530,"formatting":{"charParams":[{"r":555,"b":2122,"t":2088,"l":530,"content":2},{"r":581,"b":2123,"t":2087,"l":556,"content":0},{"r":749,"b":2123,"t":2087,"isTab":1,"l":582},{"r":778,"b":2122,"t":2089,"l":750,"content":"X"}],"lang":"EnglishUnitedStates"}},"align":"Justified","lineSpacing":1160}},"height":65},{"width":743,"text":{"par":{"lineSpacing":-1}},"height":65}]},{"cell":[{"colSpan":2,"width":1108,"text":{"par":{"leftIndent":5500,"line":{"r":779,"b":2185,"t":2150,"baseline":2185,"l":532,"formatting":{"charParams":[{"r":552,"b":2184,"t":2150,"l":532,"content":1},{"r":581,"b":2184,"t":2150,"l":557,"content":0},{"r":748,"b":2185,"t":2150,"isTab":1,"l":582},{"r":779,"b":2185,"t":2151,"l":749,"content":"X"}],"lang":"EnglishUnitedStates"}},"align":"Justified","lineSpacing":1160}},"height":59},{"width":743,"text":{"par":{"lineSpacing":-1}},"height":59}]},{"cell":[{"colSpan":2,"width":1108,"text":{"par":{"leftIndent":6200,"line":{"r":778,"b":2244,"t":2211,"baseline":2245,"l":560,"formatting":{"charParams":[{"r":584,"b":2244,"t":2211,"l":560,"content":5},{"r":749,"b":2244,"t":2211,"isTab":1,"l":585},{"r":778,"b":2244,"t":2211,"l":750,"content":"X"}],"lang":"EnglishUnitedStates"}},"align":"Justified","lineSpacing":1160}},"height":60},{"width":743,"text":{"par":{"lineSpacing":-1}},"height":60}]},{"cell":{"colSpan":3,"width":1851,"text":{"par":{"line":{"r":1972,"b":2340,"t":2273,"baseline":2329,"l":330,"formatting":{"charParams":[{"r":357,"b":2329,"t":2293,"l":330,"content":"C"},{"r":384,"b":2328,"t":2292,"l":359,"content":"h"},{"r":411,"b":2329,"t":2301,"l":387,"content":"e"},{"r":438,"b":2337,"t":2301,"l":413,"content":"q"},{"r":465,"b":2329,"t":2302,"l":441,"content":"u"},{"r":489,"b":2329,"t":2300,"l":467,"content":"e"},{"r":506,"b":2335,"t":2291,"l":490},{"r":524,"b":2335,"t":2291,"l":507,"content":"/"},{"r":542,"b":2335,"t":2291,"l":525},{"r":573,"b":2327,"t":2293,"l":543,"content":"D"},{"r":599,"b":2328,"t":2300,"l":574,"content":"e"},{"r":639,"b":2327,"t":2300,"l":601,"content":"m"},{"r":664,"b":2329,"t":2301,"l":642,"content":"a"},{"r":693,"b":2327,"t":2301,"l":669,"content":"n"},{"r":719,"b":2328,"t":2292,"l":694,"content":"d"},{"r":738,"b":2328,"t":2292,"l":720},{"r":769,"b":2327,"t":2295,"l":739,"content":"D"},{"r":789,"b":2326,"t":2302,"l":772,"content":"r"},{"r":812,"b":2328,"t":2301,"l":789,"content":"a"},{"r":844,"b":2327,"t":2292,"l":813,"content":"f"},{"r":844,"b":2327,"t":2292,"l":813,"content":"t"},{"r":875,"b":2327,"t":2292,"l":845},{"r":903,"b":2326,"t":2294,"l":876,"content":"N"},{"r":932,"b":2329,"t":2300,"l":906,"content":"o"},{"r":947,"b":2329,"t":2292,"l":933},{"r":979,"b":2328,"t":2293,"l":948,"content":"f"},{"r":979,"b":2328,"t":2293,"l":948,"content":"t"},{"r":994,"b":2328,"t":2293,"l":980},{"r":1025,"b":2327,"t":2294,"l":995,"content":"D"},{"r":1051,"b":2329,"t":2301,"l":1027,"content":"a"},{"r":1068,"b":2329,"t":2295,"l":1052,"content":"t"},{"r":1093,"b":2329,"t":2301,"l":1069,"content":"e"},{"r":1109,"b":2328,"t":2301,"l":1098,"content":":"},{"r":1147,"b":2328,"t":2300,"l":1110},{"r":1234,"b":2326,"t":2320,"isTab":1,"l":1148,"content":"."},{"r":1572,"b":2327,"t":2320,"isTab":1,"l":1454,"content":"."},{"r":1623,"b":2329,"t":2292,"l":1592,"content":"f"},{"r":1623,"b":2329,"t":2292,"suspicious":1,"l":1592,"content":"t"},{"r":1669,"b":2328,"t":2276,"suspicious":1,"l":1637,"content":4},{"r":1691,"b":2327,"t":2275,"l":1672,"content":"?"},{"r":1693,"b":2327,"t":2316,"l":1685,"content":"."},{"r":1704,"b":2326,"t":2317,"l":1697,"content":"."},{"r":1722,"b":2334,"t":2292,"l":1706,"content":"/"},{"r":1735,"b":2327,"t":2316,"l":1726,"content":"."},{"r":1745,"b":2327,"t":2317,"l":1738,"content":"."},{"r":1760,"b":2327,"t":2275,"l":1750,"content":"!"},{"r":1794,"b":2327,"t":2275,"suspicious":1,"l":1762,"content":"l"},{"r":1813,"b":2335,"t":2292,"l":1795,"content":"/"},{"r":1840,"b":2327,"t":2293,"l":1816,"content":2},{"r":1867,"b":2329,"t":2293,"l":1842,"content":"o"},{"r":1907,"b":2327,"t":2275,"suspicious":1,"l":1870,"content":"J"},{"r":1913,"b":2327,"t":2317,"l":1906,"content":"."},{"r":1940,"b":2327,"t":2275,"l":1913,"content":"i"},{"r":1959,"b":2329,"t":2316,"suspicious":1,"l":1939,"content":"»"},{"r":1972,"b":2330,"t":2316,"l":1962,"content":"."}],"lang":"EnglishUnitedStates"}},"align":"Justified","lineSpacing":1550}},"height":105}},{"cell":[{"colSpan":2,"rightBorder":"White","width":1108,"text":{"par":{"leftIndent":1700,"line":{"r":1372,"b":2441,"t":2398,"baseline":2434,"l":376,"formatting":{"charParams":[{"r":403,"b":2433,"t":2401,"l":376,"content":"B"},{"r":427,"b":2434,"t":2408,"l":405,"content":"a"},{"r":455,"b":2433,"t":2408,"l":431,"content":"n"},{"r":484,"b":2433,"t":2398,"l":459,"content":"k"},{"r":497,"b":2440,"t":2398,"l":484},{"r":515,"b":2440,"t":2398,"l":497,"content":"/"},{"r":532,"b":2440,"t":2398,"l":515},{"r":561,"b":2432,"t":2399,"l":532,"content":"B"},{"r":579,"b":2433,"t":2408,"l":561,"content":"r"},{"r":602,"b":2432,"t":2407,"l":578,"content":"a"},{"r":630,"b":2432,"t":2408,"l":606,"content":"n"},{"r":653,"b":2434,"t":2408,"l":632,"content":"c"},{"r":678,"b":2433,"t":2399,"l":654,"content":"h"},{"r":696,"b":2434,"t":2399,"l":678},{"r":722,"b":2434,"t":2408,"l":696,"content":"o"},{"r":748,"b":2433,"t":2408,"l":722,"content":"n"},{"r":766,"b":2433,"t":2400,"l":748},{"r":809,"b":2433,"t":2400,"l":766,"content":"W"},{"r":833,"b":2432,"t":2399,"l":810,"content":"h"},{"r":844,"b":2432,"t":2398,"l":835,"content":"i"},{"r":869,"b":2434,"t":2408,"l":847,"content":"c"},{"r":894,"b":2433,"t":2398,"l":870,"content":"h"},{"r":911,"b":2433,"t":2398,"l":895},{"r":942,"b":2433,"t":2399,"l":912,"content":"D"},{"r":962,"b":2433,"t":2408,"l":945,"content":"r"},{"r":986,"b":2433,"t":2408,"l":962,"content":"a"},{"r":1021,"b":2433,"t":2408,"l":989,"content":"w"},{"r":1045,"b":2433,"t":2408,"l":1021,"content":"n"},{"r":1062,"b":2434,"t":2409,"l":1053,"content":":"},{"r":1150,"b":2434,"t":2425,"isTab":1,"l":1086,"content":"."},{"r":1164,"b":2434,"t":2425,"isTab":1,"suspicious":1,"l":1156,"content":"."},{"r":1220,"b":2435,"t":2425,"isTab":1,"l":1168,"content":"."},{"r":1232,"b":2433,"t":2425,"isTab":1,"suspicious":1,"l":1224,"content":"."},{"r":1350,"b":2435,"t":2424,"isTab":1,"l":1236,"content":"."},{"r":1372,"b":2434,"t":2425,"isTab":1,"suspicious":1,"l":1354,"content":"."}],"lang":"EnglishUnitedStates"}},"align":"Justified","lineSpacing":1550}},"height":107},{"leftBorder":"White","width":743,"text":{"par":{"line":{"r":1732,"b":2416,"t":2384,"baseline":2414,"l":1414,"formatting":{"charParams":[{"r":1433,"b":2414,"t":2386,"l":1414,"content":"S"},{"r":1458,"b":2414,"t":2385,"l":1439,"content":"B"},{"r":1474,"b":2413,"t":2385,"l":1464,"content":"I"},{"r":1485,"b":2414,"t":2385,"l":1475},{"r":1509,"b":2414,"t":2385,"l":1486,"content":"T"},{"r":1522,"b":2414,"t":2385,"l":1511,"content":"I"},{"r":1554,"b":2414,"t":2385,"l":1527,"content":"D"},{"r":1585,"b":2414,"t":2386,"l":1556,"content":"A"},{"r":1610,"b":2414,"t":2386,"l":1587,"content":"L"},{"r":1620,"b":2414,"t":2386,"l":1611},{"r":1641,"b":2414,"t":2386,"l":1621,"content":"P"},{"r":1672,"b":2414,"t":2385,"l":1643,"content":"A"},{"r":1700,"b":2414,"t":2385,"l":1675,"content":"R"},{"r":1732,"b":2415,"t":2386,"l":1703,"content":"K"}],"lang":"EnglishUnitedStates"}},"align":"Justified","lineSpacing":1110}},"height":107}]},{"cell":{"colSpan":3,"width":1851,"text":{"par":{"leftIndent":100,"line":{"r":1459,"b":2633,"t":2584,"baseline":2620,"l":999,"formatting":{"charParams":[{"r":1027,"b":2618,"t":2585,"l":999,"content":"D"},{"r":1053,"b":2618,"t":2593,"l":1027,"content":"e"},{"r":1080,"b":2633,"t":2593,"l":1057,"content":"p"},{"r":1108,"b":2619,"t":2592,"l":1083,"content":"o"},{"r":1129,"b":2619,"t":2593,"l":1108,"content":"s"},{"r":1140,"b":2619,"t":2585,"l":1129,"content":"i"},{"r":1158,"b":2619,"t":2587,"l":1141,"content":"t"},{"r":1183,"b":2619,"t":2594,"l":1158,"content":"o"},{"r":1203,"b":2620,"t":2593,"l":1187,"content":"r"},{"r":1213,"b":2597,"t":2584,"l":1203,"content":"'"},{"r":1236,"b":2619,"t":2593,"l":1214,"content":"s"},{"r":1250,"b":2619,"t":2584,"l":1237},{"r":1278,"b":2620,"t":2584,"l":1251,"content":"S"},{"r":1288,"b":2619,"t":2585,"l":1278,"content":"i"},{"r":1316,"b":2625,"t":2594,"l":1290,"content":"g"},{"r":1344,"b":2619,"t":2594,"l":1319,"content":"n"},{"r":1371,"b":2619,"t":2594,"l":1348,"content":"a"},{"r":1389,"b":2619,"t":2587,"l":1370,"content":"t"},{"r":1414,"b":2619,"t":2594,"l":1392,"content":"u"},{"r":1434,"b":2619,"t":2594,"l":1418,"content":"r"},{"r":1459,"b":2619,"t":2594,"l":1434,"content":"e"}],"lang":"EnglishUnitedStates"}},"align":"Center","lineSpacing":1160}},"height":165}}],"l":302,"region":{"rect":[{"r":1457,"b":691,"t":690,"l":1174},{"r":1568,"b":692,"t":691,"l":964},{"r":1839,"b":693,"t":692,"l":834},{"r":2154,"b":694,"t":693,"l":302},{"r":2154,"b":1124,"t":694,"l":302},{"r":2154,"b":1256,"t":1124,"l":303},{"r":2155,"b":2388,"t":1256,"l":303},{"r":2155,"b":2555,"t":2388,"l":304},{"r":2156,"b":2633,"t":2555,"l":304},{"r":2156,"b":2634,"t":2633,"l":910},{"r":2156,"b":2635,"t":2634,"l":1711},{"r":2156,"b":2636,"t":2635,"l":1894},{"r":2156,"b":2637,"t":2636,"l":2076}]}},{"r":2165,"b":2836,"t":2802,"blockName":"","blockType":"Text","text":{"par":{"leftIndent":34600,"line":{"r":2159,"b":2829,"t":2808,"baseline":2823,"l":1914,"formatting":{"charParams":[{"r":1928,"b":2827,"t":2809,"l":1914,"content":"s"},{"r":1943,"b":2827,"t":2809,"suspicious":1,"l":1926,"content":"*"},{"r":1949,"b":2827,"t":2809,"suspicious":1,"l":1941,"content":"t"},{"r":1967,"b":2827,"t":2809,"suspicious":1,"l":1956,"content":"f"},{"r":1988,"b":2828,"t":2809,"l":1965,"content":"o"},{"r":2000,"b":2826,"t":2808,"suspicious":1,"l":1986,"content":"*"},{"r":2027,"b":2827,"t":2808,"suspicious":1,"l":2003,"content":"M"},{"r":2036,"b":2827,"t":2808,"suspicious":1,"l":2025,"content":"s"},{"r":2064,"b":2827,"t":2808,"l":2043,"content":"r"},{"r":2070,"b":2826,"t":2809,"l":2062,"content":"r"},{"r":2089,"b":2827,"t":2808,"l":2075,"content":"«"},{"r":2105,"b":2828,"t":2809,"suspicious":1,"l":2091,"content":5},{"r":2121,"b":2827,"t":2809,"l":2106,"content":7},{"r":2132,"b":2827,"t":2809,"l":2119,"content":"?"},{"r":2147,"b":2827,"t":2809,"suspicious":1,"l":2131,"content":"«"},{"r":2159,"b":2827,"t":2809,"l":2149,"content":";"}],"lang":"EnglishUnitedStates"}},"lineSpacing":940}},"l":1908,"region":{"rect":[{"r":2079,"b":2803,"t":2802,"l":1908},{"r":2165,"b":2835,"t":2803,"l":1908},{"r":2165,"b":2836,"t":2835,"l":2078}]}},{"r":2156,"b":2637,"t":690,"blockName":"","separatorsBox":{"separator":[{"thickness":6,"start":{"x":309,"y":698},"end":{"x":2157,"y":698},"type":"Black"},{"thickness":5,"start":{"x":306,"y":2629},"end":{"x":2150,"y":2629},"type":"Black"},{"thickness":6,"start":{"x":310,"y":696},"end":{"x":310,"y":2633},"type":"Black"},{"thickness":7,"start":{"x":2150,"y":696},"end":{"x":2150,"y":2630},"type":"Black"}]},"blockType":"SeparatorsBox","l":302,"region":{"rect":[{"r":1457,"b":691,"t":690,"l":1174},{"r":1568,"b":692,"t":691,"l":964},{"r":1839,"b":693,"t":692,"l":834},{"r":2154,"b":694,"t":693,"l":305},{"r":2154,"b":698,"t":694,"l":302},{"r":2154,"b":699,"t":698,"l":302},{"r":2154,"b":700,"t":699,"l":302},{"r":2154,"b":701,"t":700,"l":302},{"r":2154,"b":1104,"t":701,"l":302},{"r":2154,"b":1124,"t":1104,"l":302},{"r":2154,"b":1256,"t":1124,"l":303},{"r":2155,"b":2388,"t":1256,"l":303},{"r":2155,"b":2555,"t":2388,"l":304},{"r":2156,"b":2623,"t":2555,"l":304},{"r":2156,"b":2624,"t":2623,"l":304},{"r":2156,"b":2625,"t":2624,"l":304},{"r":2156,"b":2626,"t":2625,"l":304},{"r":2156,"b":2627,"t":2626,"l":304},{"r":2156,"b":2633,"t":2627,"l":304},{"r":2149,"b":2634,"t":2633,"l":910},{"r":2149,"b":2635,"t":2634,"l":1711},{"r":2149,"b":2636,"t":2635,"l":1894},{"r":2149,"b":2637,"t":2636,"l":2076}]}},{"r":2153,"b":792,"t":784,"blockName":"","blockType":"Separator","l":519,"region":{"rect":[{"r":1437,"b":785,"t":784,"l":1206},{"r":1749,"b":786,"t":785,"l":842},{"r":2153,"b":787,"t":786,"l":519},{"r":2153,"b":789,"t":787,"l":519},{"r":2153,"b":790,"t":789,"l":519},{"r":2153,"b":791,"t":790,"l":519},{"r":2153,"b":792,"t":791,"l":614}]},"separator":{"thickness":5,"start":{"x":523,"y":791},"end":{"x":2156,"y":791},"type":"Black"}},{"r":2153,"b":882,"t":874,"blockName":"","blockType":"Separator","l":305,"region":{"rect":[{"r":1081,"b":875,"t":874,"l":1075},{"r":1416,"b":876,"t":875,"l":850},{"r":2152,"b":877,"t":876,"l":305},{"r":2152,"b":879,"t":877,"l":305},{"r":2152,"b":880,"t":879,"l":305},{"r":2153,"b":881,"t":880,"l":305},{"r":2153,"b":882,"t":881,"l":616}]},"separator":{"thickness":4,"start":{"x":309,"y":881},"end":{"x":2156,"y":881},"type":"Black"}},{"r":1923,"b":953,"t":946,"blockName":"","blockType":"Separator","l":1715,"region":{"rect":{"r":1923,"b":953,"t":946,"l":1715}},"separator":{"thickness":7,"start":{"x":1718,"y":951},"end":{"x":1926,"y":951},"type":"Black"}},{"r":2152,"b":976,"t":966,"blockName":"","blockType":"Separator","l":305,"region":{"rect":[{"r":1334,"b":967,"t":966,"l":1323},{"r":1632,"b":968,"t":967,"l":861},{"r":2152,"b":969,"t":968,"l":305},{"r":2152,"b":973,"t":969,"l":305},{"r":2152,"b":974,"t":973,"l":305},{"r":2152,"b":975,"t":974,"l":616},{"r":1552,"b":976,"t":975,"l":1510}]},"separator":{"thickness":6,"start":{"x":309,"y":974},"end":{"x":2155,"y":974},"type":"Black"}},{"r":2144,"b":1066,"t":1059,"blockName":"","blockType":"Separator","l":306,"region":{"rect":[{"r":1613,"b":1060,"t":1059,"l":874},{"r":2144,"b":1061,"t":1060,"l":306},{"r":2144,"b":1065,"t":1061,"l":306},{"r":2144,"b":1066,"t":1065,"l":1032}]},"separator":{"thickness":5,"start":{"x":310,"y":1065},"end":{"x":2147,"y":1065},"type":"Black"}},{"r":2152,"b":1158,"t":1149,"blockName":"","blockType":"Separator","l":306,"region":{"rect":[{"r":1466,"b":1150,"t":1149,"l":890},{"r":2120,"b":1151,"t":1150,"l":306},{"r":2152,"b":1156,"t":1151,"l":306},{"r":2152,"b":1157,"t":1156,"l":611},{"r":1599,"b":1158,"t":1157,"l":1597}]},"separator":{"thickness":6,"start":{"x":309,"y":1155},"end":{"x":2155,"y":1155},"type":"Black"}},{"r":2152,"b":1209,"t":1201,"blockName":"","blockType":"Separator","l":306,"region":{"rect":[{"r":1590,"b":1202,"t":1201,"l":904},{"r":2060,"b":1203,"t":1202,"l":306},{"r":2152,"b":1207,"t":1203,"l":306},{"r":2152,"b":1208,"t":1207,"l":608},{"r":2152,"b":1209,"t":1208,"l":1143}]},"separator":{"thickness":6,"start":{"x":309,"y":1207},"end":{"x":2155,"y":1207},"type":"Black"}},{"r":2153,"b":1301,"t":1292,"blockName":"","blockType":"Separator","l":305,"region":{"rect":[{"r":1574,"b":1293,"t":1292,"l":951},{"r":1979,"b":1294,"t":1293,"l":305},{"r":2153,"b":1296,"t":1294,"l":305},{"r":2152,"b":1298,"t":1296,"l":305},{"r":2152,"b":1299,"t":1298,"l":603},{"r":2152,"b":1300,"t":1299,"l":1418},{"r":2152,"b":1301,"t":1300,"l":2146}]},"separator":{"thickness":5,"start":{"x":308,"y":1298},"end":{"x":2155,"y":1298},"type":"Black"}},{"r":2152,"b":1392,"t":1382,"blockName":"","blockType":"Separator","l":305,"region":{"rect":[{"r":1373,"b":1383,"t":1382,"l":1084},{"r":1895,"b":1384,"t":1383,"l":305},{"r":2152,"b":1390,"t":1384,"l":305},{"r":2152,"b":1391,"t":1390,"l":593},{"r":1888,"b":1392,"t":1391,"l":1886}]},"separator":{"thickness":6,"start":{"x":308,"y":1388},"end":{"x":2154,"y":1388},"type":"Black"}},{"r":2000,"b":1482,"t":1474,"blockName":"","blockType":"Separator","l":497,"region":{"rect":[{"r":1138,"b":1475,"t":1474,"l":1116},{"r":1804,"b":1476,"t":1475,"l":497},{"r":2000,"b":1480,"t":1476,"l":509},{"r":2000,"b":1481,"t":1480,"l":573},{"r":1598,"b":1482,"t":1481,"l":573}]},"separator":{"thickness":5,"start":{"x":500,"y":1480},"end":{"x":2002,"y":1480},"type":"Black"}},{"r":464,"b":1481,"t":1477,"blockName":"","blockType":"Separator","l":305,"region":{"rect":{"r":464,"b":1481,"t":1477,"l":305}},"separator":{"thickness":3,"start":{"x":308,"y":1480},"end":{"x":467,"y":1480},"type":"Black"}},{"r":2151,"b":1573,"t":1565,"blockName":"","blockType":"Separator","l":306,"region":{"rect":[{"r":1509,"b":1566,"t":1565,"l":1139},{"r":1722,"b":1567,"t":1566,"l":306},{"r":2151,"b":1571,"t":1567,"l":306},{"r":2151,"b":1572,"t":1571,"l":554},{"r":2144,"b":1573,"t":1572,"l":1711}]},"separator":{"thickness":5,"start":{"x":309,"y":1571},"end":{"x":2153,"y":1571},"type":"Black"}},{"r":2151,"b":1664,"t":1657,"blockName":"","blockType":"Separator","l":305,"region":{"rect":[{"r":1462,"b":1658,"t":1657,"l":1165},{"r":1647,"b":1659,"t":1658,"l":305},{"r":2151,"b":1662,"t":1659,"l":305},{"r":2151,"b":1663,"t":1662,"l":305},{"r":2151,"b":1664,"t":1663,"l":1646}]},"separator":{"thickness":5,"start":{"x":308,"y":1662},"end":{"x":2153,"y":1662},"type":"Black"}},{"r":2096,"b":1738,"t":1729,"blockName":"","blockType":"Separator","l":900,"region":{"rect":[{"r":1423,"b":1730,"t":1729,"l":1190},{"r":1625,"b":1731,"t":1730,"l":900},{"r":2096,"b":1736,"t":1731,"l":900},{"r":1625,"b":1737,"t":1736,"l":900},{"r":1625,"b":1738,"t":1737,"l":1622}]},"separator":{"thickness":6,"start":{"x":902,"y":1735},"end":{"x":2098,"y":1735},"type":"Black"}},{"r":2151,"b":1772,"t":1763,"blockName":"","blockType":"Separator","l":305,"region":{"rect":[{"r":1544,"b":1764,"t":1763,"l":1126},{"r":2151,"b":1770,"t":1764,"l":305},{"r":2151,"b":1771,"t":1770,"l":305},{"r":1816,"b":1772,"t":1771,"l":1807}]},"separator":{"thickness":6,"start":{"x":308,"y":1767},"end":{"x":2153,"y":1767},"type":"Black"}},{"r":2151,"b":1863,"t":1855,"blockName":"","blockType":"Separator","l":305,"region":{"rect":[{"r":1416,"b":1856,"t":1855,"l":1150},{"r":1728,"b":1857,"t":1856,"l":305},{"r":2137,"b":1858,"t":1857,"l":305},{"r":2151,"b":1861,"t":1858,"l":305},{"r":2151,"b":1862,"t":1861,"l":1502},{"r":2151,"b":1863,"t":1862,"l":2137}]},"separator":{"thickness":5,"start":{"x":308,"y":1859},"end":{"x":2153,"y":1859},"type":"Black"}},{"r":2150,"b":1915,"t":1907,"blockName":"","blockType":"Separator","l":305,"region":{"rect":[{"r":1696,"b":1908,"t":1907,"l":1163},{"r":2068,"b":1909,"t":1908,"l":305},{"r":2150,"b":1913,"t":1909,"l":305},{"r":2150,"b":1914,"t":1913,"l":305},{"r":2143,"b":1915,"t":1914,"l":1455}]},"separator":{"thickness":5,"start":{"x":308,"y":1911},"end":{"x":2152,"y":1911},"type":"Black"}},{"r":2150,"b":1969,"t":1961,"blockName":"","blockType":"Separator","l":305,"region":{"rect":[{"r":1412,"b":1962,"t":1961,"l":1183},{"r":1666,"b":1963,"t":1962,"l":305},{"r":1999,"b":1964,"t":1963,"l":305},{"r":2150,"b":1967,"t":1964,"l":305},{"r":2150,"b":1968,"t":1967,"l":1404},{"r":2150,"b":1969,"t":1968,"l":1787}]},"separator":{"thickness":5,"start":{"x":308,"y":1965},"end":{"x":2152,"y":1965},"type":"Black"}},{"r":2150,"b":2024,"t":2014,"blockName":"","blockType":"Separator","l":305,"region":{"rect":[{"r":1353,"b":2015,"t":2014,"l":1218},{"r":1648,"b":2016,"t":2015,"l":305},{"r":1948,"b":2017,"t":2016,"l":305},{"r":2150,"b":2021,"t":2017,"l":305},{"r":2150,"b":2022,"t":2021,"l":305},{"r":2150,"b":2023,"t":2022,"l":1408},{"r":1646,"b":2024,"t":2023,"l":1645}]},"separator":{"thickness":6,"start":{"x":308,"y":2019},"end":{"x":2152,"y":2019},"type":"Black"}},{"r":2150,"b":2078,"t":2069,"blockName":"","blockType":"Separator","l":305,"region":{"rect":[{"r":1631,"b":2070,"t":2069,"l":305},{"r":1905,"b":2071,"t":2070,"l":305},{"r":2150,"b":2076,"t":2071,"l":305},{"r":1905,"b":2077,"t":2076,"l":1627},{"r":1905,"b":2078,"t":2077,"l":1896}]},"separator":{"thickness":6,"start":{"x":308,"y":2073},"end":{"x":2152,"y":2073},"type":"Black"}},{"r":2150,"b":2143,"t":2135,"blockName":"","blockType":"Separator","l":305,"region":{"rect":[{"r":1859,"b":2136,"t":2135,"l":305},{"r":2112,"b":2137,"t":2136,"l":305},{"r":2150,"b":2141,"t":2137,"l":305},{"r":2150,"b":2142,"t":2141,"l":800},{"r":2150,"b":2143,"t":2142,"l":2105}]},"separator":{"thickness":6,"start":{"x":308,"y":2138},"end":{"x":2152,"y":2138},"type":"Black"}},{"r":2150,"b":2202,"t":2193,"blockName":"","blockType":"Separator","l":305,"region":{"rect":[{"r":1415,"b":2194,"t":2193,"l":1109},{"r":1822,"b":2195,"t":2194,"l":305},{"r":2059,"b":2196,"t":2195,"l":305},{"r":2150,"b":2200,"t":2196,"l":305},{"r":2150,"b":2201,"t":2200,"l":305},{"r":2150,"b":2202,"t":2201,"l":969}]},"separator":{"thickness":7,"start":{"x":308,"y":2197},"end":{"x":2152,"y":2197},"type":"Black"}},{"r":2150,"b":2261,"t":2253,"blockName":"","blockType":"Separator","l":304,"region":{"rect":[{"r":1586,"b":2254,"t":2253,"l":1123},{"r":1793,"b":2255,"t":2254,"l":304},{"r":2015,"b":2256,"t":2255,"l":304},{"r":2150,"b":2259,"t":2256,"l":304},{"r":2031,"b":2260,"t":2259,"l":304},{"r":1790,"b":2261,"t":2260,"l":949}]},"separator":{"thickness":5,"start":{"x":307,"y":2257},"end":{"x":2152,"y":2257},"type":"Black"}},{"r":2150,"b":2367,"t":2359,"blockName":"","blockType":"Separator","l":304,"region":{"rect":[{"r":1749,"b":2360,"t":2359,"l":304},{"r":1944,"b":2361,"t":2360,"l":304},{"r":2139,"b":2362,"t":2361,"l":304},{"r":2150,"b":2364,"t":2362,"l":304},{"r":2150,"b":2365,"t":2364,"l":304},{"r":2150,"b":2366,"t":2365,"l":1549},{"r":2150,"b":2367,"t":2366,"l":2134}]},"separator":{"thickness":5,"start":{"x":307,"y":2362},"end":{"x":2152,"y":2362},"type":"Black"}},{"r":2150,"b":2473,"t":2466,"blockName":"","blockType":"Separator","l":304,"region":{"rect":[{"r":1316,"b":2467,"t":2466,"l":332},{"r":2081,"b":2468,"t":2467,"l":304},{"r":2150,"b":2472,"t":2468,"l":304},{"r":2150,"b":2473,"t":2472,"l":304}]},"separator":{"thickness":5,"start":{"x":306,"y":2469},"end":{"x":2152,"y":2469},"type":"Black"}},{"r":2479,"b":3507,"t":3505,"blockName":"","blockType":"Separator","l":0,"region":{"rect":[{"r":1585,"b":3506,"t":3505,"l":0},{"r":2479,"b":3507,"t":3506,"l":261}]},"separator":{"thickness":1,"start":{"x":0,"y":3506},"end":{"x":2484,"y":3506},"type":"Black"}},{"r":523,"b":880,"t":694,"blockName":"","blockType":"Separator","l":517,"region":{"rect":[{"r":523,"b":830,"t":694,"l":518},{"r":523,"b":880,"t":830,"l":517}]},"separator":{"thickness":5,"start":{"x":524,"y":695},"end":{"x":524,"y":882},"type":"Black"}},{"r":1416,"b":2258,"t":1765,"blockName":"","blockType":"Separator","l":1407,"region":{"rect":[{"r":1416,"b":1855,"t":1765,"l":1410},{"r":1415,"b":1942,"t":1855,"l":1409},{"r":1414,"b":1960,"t":1942,"l":1410},{"r":1414,"b":1961,"t":1960,"l":1409},{"r":1415,"b":1981,"t":1961,"l":1409},{"r":1414,"b":2016,"t":1981,"l":1410},{"r":1415,"b":2025,"t":2016,"l":1409},{"r":1414,"b":2068,"t":2025,"l":1409},{"r":1415,"b":2076,"t":2068,"l":1409},{"r":1414,"b":2112,"t":2076,"l":1409},{"r":1414,"b":2123,"t":2112,"l":1408},{"r":1414,"b":2127,"t":2123,"l":1409},{"r":1414,"b":2134,"t":2127,"l":1408},{"r":1415,"b":2142,"t":2134,"l":1408},{"r":1414,"b":2193,"t":2142,"l":1408},{"r":1415,"b":2194,"t":2193,"l":1408},{"r":1415,"b":2201,"t":2194,"l":1407},{"r":1415,"b":2202,"t":2201,"l":1408},{"r":1414,"b":2258,"t":2202,"l":1408}]},"separator":{"thickness":5,"start":{"x":1413,"y":1766},"end":{"x":1413,"y":2259},"type":"Black"}},{"r":1417,"b":1662,"t":1202,"blockName":"","blockType":"Separator","l":1410,"region":{"rect":[{"r":1417,"b":1237,"t":1202,"l":1410},{"r":1417,"b":1291,"t":1237,"l":1411},{"r":1417,"b":1300,"t":1291,"l":1410},{"r":1416,"b":1382,"t":1300,"l":1411},{"r":1417,"b":1390,"t":1382,"l":1410},{"r":1416,"b":1662,"t":1390,"l":1410}]},"separator":{"thickness":6,"start":{"x":1415,"y":1205},"end":{"x":1415,"y":1665},"type":"Black"}},{"r":1793,"b":2329,"t":2316,"blockName":"","blockType":"Separator","l":1637,"region":{"rect":[{"r":1764,"b":2317,"t":2316,"l":1637},{"r":1793,"b":2328,"t":2317,"l":1637},{"r":1793,"b":2329,"t":2328,"l":1758}]},"separator":{"thickness":12,"start":{"x":1639,"y":2321},"end":{"x":1795,"y":2321},"type":"Dotted"}},{"r":1573,"b":2329,"t":2317,"blockName":"","blockType":"Separator","l":1146,"region":{"rect":[{"r":1567,"b":2318,"t":2317,"l":1146},{"r":1573,"b":2328,"t":2318,"l":1146},{"r":1573,"b":2329,"t":2328,"l":1561}]},"separator":{"thickness":10,"start":{"x":1148,"y":2323},"end":{"x":1575,"y":2323},"type":"Dotted"}},{"r":2074,"b":2437,"t":2422,"blockName":"","blockType":"Separator","l":1086,"region":{"rect":[{"r":1514,"b":2423,"t":2422,"l":1165},{"r":1726,"b":2424,"t":2423,"l":1086},{"r":1911,"b":2425,"t":2424,"l":1086},{"r":2074,"b":2434,"t":2425,"l":1086},{"r":2074,"b":2435,"t":2434,"l":1086},{"r":2074,"b":2436,"t":2435,"l":1720},{"r":2074,"b":2437,"t":2436,"l":1904}]},"separator":{"thickness":10,"start":{"x":1088,"y":2428},"end":{"x":2076,"y":2428},"type":"Dotted"}}],"originalCoords":1,"resolution":300,"height":3507},"version":1}}